archvyrt/__init__.py
archvyrt/__main__.py
archvyrt/domain.py
archvyrt/tools.py
archvyrt/version.py
archvyrt/libvirt/__init__.py
archvyrt/libvirt/disk.py
archvyrt/libvirt/domain.py
archvyrt/libvirt/network.py
archvyrt/libvirt/rng.py
archvyrt/libvirt/xml.py
archvyrt/provisioner/__init__.py
archvyrt/provisioner/archlinux.py
archvyrt/provisioner/base.py
archvyrt/provisioner/plain.py
archvyrt/provisioner/ubuntu.py
archvyrt/provisioner/base/__init__.py
archvyrt/provisioner/base/linux.py
archvyrt-0.6.1.dist-info/DESCRIPTION.rst
archvyrt-0.6.1.dist-info/METADATA
archvyrt-0.6.1.dist-info/RECORD
archvyrt-0.6.1.dist-info/WHEEL
archvyrt-0.6.1.dist-info/entry_points.txt
archvyrt-0.6.1.dist-info/metadata.json
archvyrt-0.6.1.dist-info/top_level.txt
