Metadata-Version: 2.0
Name: archvyrt
Version: 0.6.1
Summary: libvirt provisioner for archlinux libvirt hosts
Home-page: https://github.com/andrekeller/archvyrt
Author: Andre Keller
Author-email: ak@0x2a.io
License: MIT
Platform: UNKNOWN
Classifier: Development Status :: 3 - Alpha
Classifier: Intended Audience :: System Administrators
Classifier: Topic :: System :: Systems Administration
Classifier: License :: OSI Approved :: MIT License
Classifier: Programming Language :: Python :: 3
Requires-Python: >=3.4
Requires-Dist: libvirt-python
